rapidbounce_cms/__init__.py
rapidbounce_cms/admin.py
rapidbounce_cms/apps.py
rapidbounce_cms/migrations/0001_initial.py
rapidbounce_cms/migrations/0002_auto_20210415_1709.py
rapidbounce_cms/migrations/0003_auto_20210419_1719.py
rapidbounce_cms/migrations/__init__.py
rapidbounce_cms/models.py
rapidbounce_cms/templates/admin/thumbnail.html
rapidbounce_cms/tests.py
rapidbounce_cms/translation.py
rapidbounce_cms/views.py
rapidbounce_cms-0.3.0.dist-info/WHEEL
rapidbounce_cms-0.3.0.dist-info/METADATA
rapidbounce_cms-0.3.0.dist-info/RECORD
